README.rst
setup.py
twitch_chat_wrapper/__init__.py
twitch_chat_wrapper/wrapper.py
twitch_chat_wrapper.egg-info/PKG-INFO
twitch_chat_wrapper.egg-info/SOURCES.txt
twitch_chat_wrapper.egg-info/dependency_links.txt
twitch_chat_wrapper.egg-info/requires.txt
twitch_chat_wrapper.egg-info/top_level.txt