Metadata-Version: 1.1
Name: twitch-chat-wrapper
Version: 0.4.2
Summary: Simple Twitch Chat Wrapper written in Python
Home-page: https://github.com/arthurbarros/twitch-chat-wrapper
Author: Arthur Barros
Author-email: arthbarros@gmail.com
License: Copyright (c) 2017 by Arthur Barros and contributors.  See AUTHORS
